{"is_source_file": true, "format": "JavaScript", "description": "This file defines a functional component NoteList that renders a list of notes with features for selection and deletion, based on provided parameters. It manipulates DOM elements directly, generating HTML and attaching event listeners.", "external_files": [], "external_methods": ["escapeHtml", "formatDate"], "published": ["NoteList"], "classes": [], "methods": [{"name": "NoteList(mountEl, { notes, activeId, onSelect, onDelete })", "description": "Renders a list of note items, handling selection and deletion with event listeners.", "scope": "", "scopeKind": ""}, {"name": "formatDate(iso)", "description": "Formats ISO date strings into locale strings with error handling.", "scope": "", "scopeKind": ""}, {"name": "escapeHtml(str)", "description": "Escapes special HTML characters in strings to prevent injection.", "scope": "", "scopeKind": ""}], "calls": ["formatDate", "escapeHtml"], "search-terms": ["NoteList", "notes_frontend", "render notes", "delete note", "note-item", "active note", "note list component"], "state": 2, "file_id": 14, "knowledge_revision": 29, "git_revision": "", "ctags": [{"_type": "tag", "name": "NoteList", "path": "/home/kavia/workspace/code-generation/note-organizer-23636-23683/notes_frontend/src/components/NoteList.js", "pattern": "/^export function NoteList(mountEl, { notes, activeId, onSelect, onDelete }) {$/", "language": "JavaScript", "kind": "function", "signature": "(mountEl, { notes, activeId, onSelect, onDelete })"}, {"_type": "tag", "name": "escapeHtml", "path": "/home/kavia/workspace/code-generation/note-organizer-23636-23683/notes_frontend/src/components/NoteList.js", "pattern": "/^function escapeHtml(str) {$/", "language": "JavaScript", "kind": "function", "signature": "(str)"}, {"_type": "tag", "name": "formatDate", "path": "/home/kavia/workspace/code-generation/note-organizer-23636-23683/notes_frontend/src/components/NoteList.js", "pattern": "/^function formatDate(iso) {$/", "language": "JavaScript", "kind": "function", "signature": "(iso)"}], "hash": "253f441e9add89b2738d22eac6759ad3", "format-version": 4, "code-base-name": "notes_frontend", "filename": "notes_frontend/src/components/NoteList.js", "revision_history": [{"29": ""}]}